<?xml version="1.0" encoding="UTF-8" ?>
<!DOCTYPE mapper PUBLIC "-//mybatis.org//DTD Mapper 3.0//EN" "http://mybatis.org/dtd/mybatis-3-mapper.dtd" >
<mapper namespace="com.guojijian.crm.settings.mapper.UserMapper" >
  <resultMap id="BaseResultMap" type="com.guojijian.crm.settings.pojo.User" >
    <!--
      WARNING - @mbggenerated
      This element is automatically generated by MyBatis Generator, do not modify.
      This element was generated on Sat Dec 03 22:41:29 CST 2022.
    -->
    <id column="id" property="id" jdbcType="CHAR" />
    <result column="login_act" property="loginAct" jdbcType="VARCHAR" />
    <result column="name" property="name" jdbcType="VARCHAR" />
    <result column="login_pwd" property="loginPwd" jdbcType="VARCHAR" />
    <result column="email" property="email" jdbcType="VARCHAR" />
    <result column="expire_time" property="expireTime" jdbcType="CHAR" />
    <result column="lock_state" property="lockState" jdbcType="CHAR" />
    <result column="deptno" property="deptno" jdbcType="CHAR" />
    <result column="allow_ips" property="allowIps" jdbcType="VARCHAR" />
    <result column="createTime" property="createtime" jdbcType="CHAR" />
    <result column="create_by" property="createBy" jdbcType="VARCHAR" />
    <result column="edit_time" property="editTime" jdbcType="CHAR" />
    <result column="edit_by" property="editBy" jdbcType="VARCHAR" />
  </resultMap>

  <sql id="userColumn">id,login_act,name,login_pwd,email,expire_time,lock_state,deptno,allow_ips,createTime,create_by,edit_time,edit_by</sql>

  <delete id="deleteByPrimaryKey" parameterType="java.lang.String" >
    <!--
      WARNING - @mbggenerated
      This element is automatically generated by MyBatis Generator, do not modify.
      This element was generated on Sat Dec 03 22:41:29 CST 2022.
    -->
    delete from tbl_user
    where id = #{id,jdbcType=CHAR}
  </delete>
  <insert id="insert" parameterType="com.guojijian.crm.settings.pojo.User" >
    <!--
      WARNING - @mbggenerated
      This element is automatically generated by MyBatis Generator, do not modify.
      This element was generated on Sat Dec 03 22:41:29 CST 2022.
    -->
    insert into tbl_user (id, login_act, name, 
      login_pwd, email, expire_time, 
      lock_state, deptno, allow_ips, 
      createTime, create_by, edit_time, 
      edit_by)
    values (#{id,jdbcType=CHAR}, #{loginAct,jdbcType=VARCHAR}, #{name,jdbcType=VARCHAR}, 
      #{loginPwd,jdbcType=VARCHAR}, #{email,jdbcType=VARCHAR}, #{expireTime,jdbcType=CHAR}, 
      #{lockState,jdbcType=CHAR}, #{deptno,jdbcType=CHAR}, #{allowIps,jdbcType=VARCHAR}, 
      #{createtime,jdbcType=CHAR}, #{createBy,jdbcType=VARCHAR}, #{editTime,jdbcType=CHAR}, 
      #{editBy,jdbcType=VARCHAR})
  </insert>
  <update id="updateByPrimaryKey" parameterType="com.guojijian.crm.settings.pojo.User" >
    <!--
      WARNING - @mbggenerated
      This element is automatically generated by MyBatis Generator, do not modify.
      This element was generated on Sat Dec 03 22:41:29 CST 2022.
    -->
    update tbl_user
    set login_act = #{loginAct,jdbcType=VARCHAR},
      name = #{name,jdbcType=VARCHAR},
      login_pwd = #{loginPwd,jdbcType=VARCHAR},
      email = #{email,jdbcType=VARCHAR},
      expire_time = #{expireTime,jdbcType=CHAR},
      lock_state = #{lockState,jdbcType=CHAR},
      deptno = #{deptno,jdbcType=CHAR},
      allow_ips = #{allowIps,jdbcType=VARCHAR},
      createTime = #{createtime,jdbcType=CHAR},
      create_by = #{createBy,jdbcType=VARCHAR},
      edit_time = #{editTime,jdbcType=CHAR},
      edit_by = #{editBy,jdbcType=VARCHAR}
    where id = #{id,jdbcType=CHAR}
  </update>
  <select id="selectByPrimaryKey" resultMap="BaseResultMap" parameterType="java.lang.String" >
    <!--
      WARNING - @mbggenerated
      This element is automatically generated by MyBatis Generator, do not modify.
      This element was generated on Sat Dec 03 22:41:29 CST 2022.
    -->
    select id, login_act, name, login_pwd, email, expire_time, lock_state, deptno, allow_ips, 
    createTime, create_by, edit_time, edit_by
    from tbl_user
    where id = #{id,jdbcType=CHAR}
  </select>
  <select id="selectAll" resultMap="BaseResultMap" >
    <!--
      WARNING - @mbggenerated
      This element is automatically generated by MyBatis Generator, do not modify.
      This element was generated on Sat Dec 03 22:41:29 CST 2022.
    -->
    select id, login_act, name, login_pwd, email, expire_time, lock_state, deptno, allow_ips, 
    createTime, create_by, edit_time, edit_by
    from tbl_user
  </select>

  <!--User selectUserByActAndPwd(Map<String,Object> map);-->
  <select id="selectUserByActAndPwd" resultMap="BaseResultMap">
    SELECT <include refid="userColumn"></include>
    FROM tbl_user
    WHERE login_act=#{login_act} AND login_pwd=#{login_pwd}
  </select>
</mapper>